kokoro/__init__.py
kokoro/__main__.py
kokoro/custom_stft.py
kokoro/istftnet.py
kokoro/model.py
kokoro/modules.py
kokoro/pipeline.py
kokoro-0.8.4.dist-info/METADATA
kokoro-0.8.4.dist-info/WHEEL
kokoro-0.8.4.dist-info/entry_points.txt
kokoro-0.8.4.dist-info/licenses/LICENSE
kokoro-0.8.4.dist-info/RECORD
