Metadata-Version: 2.4
Name: kokoro
Version: 0.8.4
Summary: TTS
Project-URL: Homepage, https://github.com/hexgrad/kokoros
Project-URL: Repository, https://github.com/hexgrad/kokoro
Author-email: hexgrad <hello@hexgrad.com>
License:                                  Apache License
License-File: LICENSE
Classifier: License :: OSI Approved :: Apache Software License
Classifier: Operating System :: OS Independent
Classifier: Programming Language :: Python :: 3
Requires-Python: <3.13,>=3.10
Requires-Dist: huggingface-hub
Requires-Dist: loguru
Requires-Dist: misaki[en]>=0.8.4
Requires-Dist: numpy==1.26.4
Requires-Dist: scipy
Requires-Dist: torch
Requires-Dist: transformers
